CHANGELOG.md
LICENSE
MANIFEST.in
README.md
setup.cfg
setup.py
versioneer.py
junctiontree/__init__.py
junctiontree/_meta.py
junctiontree/_version.py
junctiontree/computation.py
junctiontree/construction.py
junctiontree/junctiontree.py
junctiontree/sum_product.py
junctiontree.egg-info/PKG-INFO
junctiontree.egg-info/SOURCES.txt
junctiontree.egg-info/dependency_links.txt
junctiontree.egg-info/requires.txt
junctiontree.egg-info/top_level.txt
tests/__init__.py
tests/test_computation.py
tests/test_construction.py
tests/test_junctiontree.py
tests/util.py