Metadata-Version: 2.1
Name: junctiontree
Version: 0.2.4
Summary: Junction tree and belief propagation algorithms
Home-page: https://github.com/jluttine/junction-tree
Author: Darryl Reeves and Jaakko Luttinen
License: UNKNOWN
Keywords: probabilistic programming,Bayesian networks,graphical models
Platform: UNKNOWN
Classifier: Programming Language :: Python :: 3 :: Only
Classifier: Development Status :: 2 - Pre-Alpha
Classifier: Environment :: Console
Classifier: Intended Audience :: Developers
Classifier: Intended Audience :: Science/Research
Classifier: License :: OSI Approved :: MIT License
Classifier: Operating System :: OS Independent
Classifier: Topic :: Scientific/Engineering
Classifier: Topic :: Scientific/Engineering :: Information Analysis
